latin_nlp_utilities-1.1.0.dist-info/licenses/LICENSE
nlp_utilities/__init__.py
nlp_utilities/constants.py
nlp_utilities/loaders.py
nlp_utilities/normalizers.py
nlp_utilities/brat/__init__.py
nlp_utilities/brat/brat_to_conllu.py
nlp_utilities/brat/conllu_to_brat.py
nlp_utilities/brat/utils.py
nlp_utilities/conllu/__init__.py
nlp_utilities/conllu/evaluators/__init__.py
nlp_utilities/conllu/evaluators/base.py
nlp_utilities/conllu/evaluators/evaluator.py
nlp_utilities/conllu/evaluators/helpers.py
nlp_utilities/conllu/evaluators/tree_validation.py
nlp_utilities/conllu/evaluators/word_processing.py
nlp_utilities/conllu/validators/__init__.py
nlp_utilities/conllu/validators/character_constraints.py
nlp_utilities/conllu/validators/content_validators.py
nlp_utilities/conllu/validators/enhanced_deps.py
nlp_utilities/conllu/validators/error_reporter.py
nlp_utilities/conllu/validators/feature_format.py
nlp_utilities/conllu/validators/format.py
nlp_utilities/conllu/validators/functional_leaves.py
nlp_utilities/conllu/validators/id_sequence.py
nlp_utilities/conllu/validators/language_content.py
nlp_utilities/conllu/validators/language_format.py
nlp_utilities/conllu/validators/metadata.py
nlp_utilities/conllu/validators/misc_column.py
nlp_utilities/conllu/validators/spans.py
nlp_utilities/conllu/validators/structural_constraints.py
nlp_utilities/conllu/validators/structure.py
nlp_utilities/conllu/validators/unicode.py
nlp_utilities/conllu/validators/upos_deprel_compatibility.py
nlp_utilities/conllu/validators/validation_mixin.py
nlp_utilities/conllu/validators/validator.py
nlp_utilities/conllu/validators/helpers/__init__.py
nlp_utilities/conllu/validators/helpers/node_helpers.py
nlp_utilities/conllu/validators/helpers/tree_helpers.py
nlp_utilities/converters/__init__.py
nlp_utilities/converters/features.py
nlp_utilities/converters/upos.py
nlp_utilities/converters/xpos/__init__.py
nlp_utilities/converters/xpos/ittb_converters.py
nlp_utilities/converters/xpos/llct_converters.py
nlp_utilities/converters/xpos/proiel_converters.py
latin_nlp_utilities-1.1.0.dist-info/METADATA
latin_nlp_utilities-1.1.0.dist-info/WHEEL
latin_nlp_utilities-1.1.0.dist-info/top_level.txt
latin_nlp_utilities-1.1.0.dist-info/RECORD
