Metadata-Version: 2.4
Name: latin-nlp-utilities
Version: 1.1.0
Summary: A set of convenience tools for Natural Language Processing work with Latin treebanks and annotated corpora.
Author: Gabe Pizzorno
License-Expression: MIT
Project-URL: Homepage, https://github.com/gpizzorno/latin-nlp-utilities/
Keywords: nlp,natural-language-processing,latin,universal-dependencies,text-annotation,brat,ud,conllu,conllu-validation,conllu-evaluation,tag-conversion,tag-normalization
Classifier: Programming Language :: Python
Classifier: Programming Language :: Python :: 3
Classifier: Programming Language :: Python :: 3 :: Only
Classifier: Programming Language :: Python :: 3.8
Classifier: Programming Language :: Python :: 3.9
Classifier: Programming Language :: Python :: 3.10
Classifier: Programming Language :: Python :: 3.11
Classifier: Programming Language :: Python :: 3.12
Classifier: Operating System :: OS Independent
Requires-Python: >=3.9
License-File: LICENSE
Requires-Dist: conllu>=6.0.0
Requires-Dist: importlib_resources>=6.5.2
Requires-Dist: regex>=2024.11.6
Provides-Extra: dev
Requires-Dist: factory_boy; extra == "dev"
Requires-Dist: hypothesis; extra == "dev"
Requires-Dist: mypy; extra == "dev"
Requires-Dist: pytest; extra == "dev"
Requires-Dist: pytest-cov; extra == "dev"
Requires-Dist: pytest-mock; extra == "dev"
Provides-Extra: docs
Requires-Dist: sphinx>=7.2.0; extra == "docs"
Requires-Dist: sphinx-rtd-theme>=2.0.0; extra == "docs"
Requires-Dist: sphinx-autodoc-typehints>=1.25.0; extra == "docs"
Requires-Dist: sphinxcontrib-mermaid>=1.0.0; extra == "docs"
Requires-Dist: myst-parser>=2.0.0; extra == "docs"
Dynamic: license-file
